{
	"blocs": [
		{
			"color": "#000000",
			"page": "vert",
			"tpl_src": "/tplsnew/main_title_divs.html",
			"caterogyFilter": "Attract",
			"who": 0,
			"anchor": "Home",
			"minMenu": 1,
			"maxMenu": 4,
			"listmenu": [
				{
					"content": "Home"
				},
				{
					"content": "About us"
				},
				{
					"content": "FAQ"
				},
				{
					"content": "Contact us"
				}
			],
			"minSocial": 1,
			"maxSocial": 3,
			"listsocial": [
				{
					"social_profile_link": "https://www.tiktok.com/username/"
				},
				{
					"social_profile_link": "https://www.twitter.com/username/"
				},
				{
					"social_profile_link": "https://www.instagram.com/username/"
				}
			],
			"main_title": [
				{}
			],
			"main_subtitle": [
				{}
			],
			"title": "The Original",
			"subtitle": "hahah",
			"description": [],
			"image": "/assets/img/p1.png",
			"image_style": "has-radius",
			"logo": "https://bulma.io/images/bulma-logo.png",
			"logo_style": "has-radius",
			"maliste": [],
			"label": "Contact us",
			"keyword": "restaurant,food,portugal,lisbon"
		},
		{
			"color": "#000000",
			"page": "vert",
			"tpl_src": "/tplsnew/main_title_btn.html",
			"caterogyFilter": "Title",
			"who": 1,
			"anchor": "Home",
			"minMenu": 1,
			"maxMenu": 4,
			"listmenu": [],
			"minSocial": 1,
			"maxSocial": 3,
			"listsocial": [],
			"main_title": [
				{}
			],
			"main_subtitle": [
				{}
			],
			"title": "The Original",
			"subtitle": "hahah",
			"description": [],
			"image": "/assets/img/p1.png",
			"image_style": "has-radius",
			"logo": "https://bulma.io/images/bulma-logo.png",
			"logo_style": "has-radius",
			"maliste": [],
			"label": "Contact us",
			"keyword": "restaurant,food,portugal,lisbon"
		},
		{
			"color": "#000000",
			"type": "rj_nav",
			"keyword": "restaurant,food,portugal,lisbon",
			"tpl_src": "/tplsnew/OKhero.html",
			"caterogyFilter": "pricing",
			"who": 2,
			"anchor": "Home",
			"minMenu": 1,
			"maxMenu": 4,
			"listmenu": [],
			"minSocial": 1,
			"maxSocial": 3,
			"listsocial": [],
			"main_title": [
				{}
			],
			"main_subtitle": [
				{}
			],
			"title": "The Original",
			"subtitle": "hahah",
			"description": [],
			"image": "https://source.unsplash.com/600x600/?restaurant,food,portugal,lisbon&pic=3",
			"image_style": "has-radius",
			"logo": "https://bulma.io/images/bulma-logo.png",
			"logo_style": "has-radius",
			"maliste": [],
			"label": "Contact us"
		},
		{
			"color": "#000000",
			"type": "rj_nav",
			"keyword": "restaurant,food,portugal,lisbon",
			"tpl_src": "/tplsnew/OKhero.html",
			"caterogyFilter": "pricing",
			"who": 3,
			"anchor": "Home",
			"minMenu": 1,
			"maxMenu": 4,
			"listmenu": [],
			"minSocial": 1,
			"maxSocial": 3,
			"listsocial": [],
			"main_title": [
				{}
			],
			"main_subtitle": [
				{}
			],
			"title": "The Original",
			"subtitle": "hahah",
			"description": [],
			"image": "https://source.unsplash.com/600x600/?restaurant,food,portugal,lisbon&pic=4",
			"image_style": "has-radius",
			"logo": "https://bulma.io/images/bulma-logo.png",
			"logo_style": "has-radius",
			"maliste": [],
			"label": "Contact us"
		},
		{
			"color": "#000000",
			"type": "rj_nav",
			"keyword": "france,wine",
			"tpl_src": "/tplsnew/OKhero.html",
			"caterogyFilter": "pricing",
			"who": 4,
			"anchor": "Home",
			"minMenu": 1,
			"maxMenu": 4,
			"listmenu": [],
			"minSocial": 1,
			"maxSocial": 3,
			"listsocial": [],
			"main_title": [
				{}
			],
			"main_subtitle": [
				{}
			],
			"title": "The Original",
			"subtitle": "hahah",
			"description": [],
			"image": "https://cdn.jsdelivr.net/gh/GalinhaLX/hello2@43ad809c6fdde38b794092ba3ecd740f840e5ce5/images/9b7c2bcf-699e-4c27-afb0-36af3c1b08b6",
			"image_style": "has-radius",
			"logo": "https://bulma.io/images/bulma-logo.png",
			"logo_style": "has-radius",
			"maliste": [],
			"label": "Contact us"
		}
	]
}